keeper_pam_webrtc_rs/__init__.py
keeper_pam_webrtc_rs/keeper_pam_webrtc_rs.abi3.so
keeper_pam_webrtc_rs-1.2.5.dist-info/METADATA
keeper_pam_webrtc_rs-1.2.5.dist-info/WHEEL
keeper_pam_webrtc_rs-1.2.5.dist-info/RECORD
