Metadata-Version: 2.4
Name: keeper-pam-webrtc-rs
Version: 1.2.5
Classifier: Development Status :: 5 - Production/Stable
Classifier: Intended Audience :: Developers
Classifier: Programming Language :: Python :: 3
Classifier: Programming Language :: Python :: 3.7
Classifier: Programming Language :: Python :: 3.8
Classifier: Programming Language :: Python :: 3.9
Classifier: Programming Language :: Python :: 3.10
Classifier: Programming Language :: Python :: 3.11
Classifier: Programming Language :: Python :: 3.12
Classifier: Programming Language :: Rust
Classifier: Topic :: Security
Classifier: Topic :: Communications
License-File: LICENSE
Summary: Keeper PAM WebRTC for Python - A secure, stable, and high-performance Tube API for Python, providing WebRTC-based secure tunneling with enterprise-grade security and reliability optimizations.
License-Expression: MIT
Requires-Python: >=3.7
